[{"content":"Test Data","date":"2024-01-16T18:44:27.396Z"},{"content":"Nota increíble","date":"2024-01-16T18:47:25.372Z"},{"content":"zzzzzz","date":"2024-01-16T18:47:54.033Z"},{"content":"Test Data","date":"2024-01-16T18:45:55.742Z"},{"content":"test","date":"2024-01-16T18:49:00.274Z"},{"content":"test","date":"2024-01-16T18:49:05.933Z"},{"content":"test","date":"2024-01-16T18:49:18.850Z"},{"content":"4","date":"2024-01-16T18:49:46.349Z"},{"content":"p","date":"2024-01-16T18:49:15.556Z"},{"content":"zxc","date":"2024-01-16T18:50:50.634Z"},{"content":"5","date":"2024-01-16T18:53:30.652Z"},{"content":"hello from waterloo","date":"2024-01-16T18:53:50.922Z"},{"content":"gostbusters","date":"2024-01-16T18:53:52.112Z"},{"content":"Nueva nota","date":"2024-01-16T18:54:16.137Z"},{"content":"p","date":"2024-01-16T18:55:27.374Z"},{"content":":)","date":"2024-01-16T18:57:18.358Z"},{"content":"Jack Skywalker","date":"2024-01-16T19:00:02.279Z"},{"content":"Hola Marbeth","date":"2024-01-16T19:01:29.958Z"},{"content":"Hola Andolyn","date":"2024-01-16T19:01:40.677Z"},{"content":"Hola Lola","date":"2024-01-16T19:01:50.467Z"},{"content":"Hola Maria Jesus","date":"2024-01-16T19:02:05.615Z"},{"content":"Shoyinka Habeebullah","date":"2024-01-16T19:02:19.033Z"},{"content":"buenos dias","date":"2024-01-16T19:04:27.553Z"},{"content":"hola mundo!","date":"2024-01-16T19:05:23.624Z"},{"content":"(:","date":"2024-01-16T19:05:36.911Z"},{"content":"-","date":"2024-01-16T19:08:01.115Z"},{"content":"lulu sama","date":"2024-01-16T19:17:38.882Z"},{"content":"Soy de Costa Rica","date":"2024-01-16T19:21:30.333Z"},{"content":"agregar elementos es papita","date":"2024-01-16T19:21:35.340Z"},{"content":"Whistle baby","date":"2024-01-16T19:21:58.848Z"},{"content":"pero vivo en Helsinki","date":"2024-01-16T19:22:23.089Z"},{"content":"Kuinka monta kertaa kutsuu","date":"2024-01-16T19:23:20.818Z"},{"content":"You guys are doing great !","date":"2024-01-16T19:24:07.540Z"},{"content":"pixie sama","date":"2024-01-16T19:26:34.324Z"},{"content":"dsa","date":"2024-01-16T19:26:11.750Z"},{"content":"Hola!","date":"2024-01-16T19:26:16.733Z"},{"content":"test test data","date":"2024-01-16T19:27:45.461Z"},{"content":"SHANE","date":"2024-01-16T19:28:08.888Z"},{"content":"test test test test","date":"2024-01-16T19:29:04.393Z"},{"content":"According to all known laws of aviation,     there is no way a bee should be able to fly.     Its wings are too small to get its fat little body off the ground.     The bee, of course, flies anyway   ","date":"2024-01-16T19:29:46.075Z"},{"content":"the apothecary diary","date":"2024-01-16T19:30:27.588Z"},{"content":"Yellow, black. Yellow, black. Yellow, black. Yellow, black.","date":"2024-01-16T19:30:05.200Z"},{"content":"Ooh, black and yellow! Let's shake it up a little.     Barry! Breakfast is ready!     Ooming!     Hang on a second.     Hello?     - Barry? - Adam?     - Oan you believe this is happening? - I can't. ","date":"2024-01-16T19:30:24.003Z"},{"content":"How's everybody doing?","date":"2024-01-16T19:31:09.090Z"},{"content":"Hola a todos","date":"2024-01-16T19:34:19.496Z"},{"content":"hoshinoko","date":"2024-01-16T19:37:21.731Z"},{"content":"test","date":"2024-01-16T19:50:23.791Z"},{"content":"the slam dunk","date":"2024-01-16T19:53:50.009Z"},{"content":"","date":"2024-01-16T19:54:32.033Z"},{"content":"testi","date":"2024-01-16T19:57:53.945Z"},{"content":"Esta genial","date":"2024-01-16T19:58:27.443Z"},{"content":"adf","date":"2024-01-16T20:09:14.252Z"},{"content":"Practice 1","date":"2024-01-16T20:19:15.353Z"},{"content":"sussissassissus","date":"2024-01-16T20:23:26.503Z"},{"content":"Test 2","date":"2024-01-16T20:34:32.333Z"},{"content":"the slam dunk final","date":"2024-01-16T20:46:18.350Z"},{"content":"asd","date":"2024-01-16T20:47:56.106Z"},{"content":"testi","date":"2024-01-16T20:48:37.268Z"},{"content":"asd","date":"2024-01-16T20:50:01.593Z"},{"content":"holaaa","date":"2024-01-16T20:53:18.564Z"},{"content":"","date":"2024-01-16T20:59:46.067Z"},{"content":"Argentina Messi ","date":"2024-01-16T21:05:19.628Z"},{"content":"@Midudev","date":"2024-01-16T21:11:45.968Z"},{"content":"testi","date":"2024-01-16T21:12:01.109Z"},{"content":"seku testailen","date":"2024-01-16T21:15:02.085Z"},{"content":"testailen toistamiseen","date":"2024-01-16T21:19:32.837Z"},{"content":"s","date":"2024-01-16T21:25:12.504Z"},{"content":"vastoin kaikkia odotuksia, testailen kolmannen kerran","date":"2024-01-16T21:28:37.155Z"},{"content":"","date":"2024-01-16T21:35:17.521Z"},{"content":"It's ok","date":"2024-01-16T21:37:20.793Z"},{"content":"My name is Falekin","date":"2024-01-16T21:52:29.565Z"},{"content":"Hello from Ukraine, 17.01.2024","date":"2024-01-16T22:01:05.043Z"},{"content":"This is a nice experience","date":"2024-01-16T22:01:28.701Z"},{"content":"TEST","date":"2024-01-16T22:06:26.546Z"},{"content":"Falekin new note","date":"2024-01-16T22:19:22.949Z"},{"content":"Falekin other new note","date":"2024-01-16T22:19:39.704Z"},{"content":"Hola desde Paraguay","date":"2024-01-16T22:19:58.589Z"},{"content":"me p3lan la reata","date":"2024-01-16T22:26:17.998Z"},{"content":"Hola desde Monterrey, MX","date":"2024-01-16T23:00:57.982Z"},{"content":"@alainlobato10 on instagram","date":"2024-01-16T23:01:29.299Z"},{"content":"Never Gonna Give You Up","date":"2024-01-16T23:05:31.097Z"},{"content":"Hola","date":"2024-01-16T23:09:37.830Z"},{"content":"hola","date":"2024-01-16T23:15:53.930Z"},{"content":"","date":"2024-01-16T23:20:14.572Z"},{"content":"","date":"2024-01-16T23:20:14.676Z"},{"content":"","date":"2024-01-16T23:20:40.917Z"},{"content":"dsdsaf","date":"2024-01-16T23:21:22.195Z"},{"content":"","date":"2024-01-16T23:24:58.087Z"},{"content":"","date":"2024-01-16T23:28:57.364Z"},{"content":"dsdadaaaaa","date":"2024-01-16T23:29:06.284Z"},{"content":"hola","date":"2024-01-16T23:29:41.091Z"},{"content":"hola a todos","date":"2024-01-16T23:51:48.785Z"},{"content":"La Zenia","date":"2024-01-16T23:58:38.630Z"},{"content":"a","date":"2024-01-17T00:19:17.976Z"},{"content":"anthony from Uganda","date":"2024-01-17T00:50:31.486Z"},{"content":"ni haom a","date":"2024-01-17T00:51:13.418Z"},{"content":"s","date":"2024-01-17T00:51:53.990Z"},{"content":"I'll give you a nickle if you tickle my pickle","date":"2024-01-17T00:56:15.502Z"},{"content":"Another One","date":"2024-01-17T00:59:22.100Z"},{"content":"Another One","date":"2024-01-17T01:19:46.403Z"}]